<?xml version="1.0" encoding="UTF-8"?>
<MetaDataObject xmlns="http://v8.1c.ru/8.3/MDClasses" xmlns:app="http://v8.1c.ru/8.2/managed-application/core" xmlns:cfg="http://v8.1c.ru/8.1/data/enterprise/current-config" xmlns:cmi="http://v8.1c.ru/8.2/managed-application/cmi" xmlns:ent="http://v8.1c.ru/8.1/data/enterprise" xmlns:lf="http://v8.1c.ru/8.2/managed-application/logform" xmlns:style="http://v8.1c.ru/8.1/data/ui/style" xmlns:sys="http://v8.1c.ru/8.1/data/ui/fonts/system" xmlns:v8="http://v8.1c.ru/8.1/data/core" xmlns:v8ui="http://v8.1c.ru/8.1/data/ui" xmlns:web="http://v8.1c.ru/8.1/data/ui/colors/web" xmlns:win="http://v8.1c.ru/8.1/data/ui/colors/windows" xmlns:xen="http://v8.1c.ru/8.3/xcf/enums" xmlns:xpr="http://v8.1c.ru/8.3/xcf/predef" xmlns:xr="http://v8.1c.ru/8.3/xcf/readable" xmlns:xs="http://www.w3.org/2001/XMLSchema" xmlns:xsi="http://www.w3.org/2001/XMLSchema-instance" version="2.6">
	<Table uuid="cf70327d-e957-4464-b534-eeebcf390ced">
		<InternalInfo>
			<xr:GeneratedType name="ExternalDataSourceTableManager.BalanceDB.www_balans_dbo_zakaz" category="Manager">
				<xr:TypeId>bebc2d8d-b555-4548-adc8-a3d06d9ef86a</xr:TypeId>
				<xr:ValueId>1e3265ab-4233-4b0f-a400-4713ac3096d5</xr:ValueId>
			</xr:GeneratedType>
			<xr:GeneratedType name="ExternalDataSourceTableObject.BalanceDB.www_balans_dbo_zakaz" category="Object">
				<xr:TypeId>b779502a-9aa0-4775-b8b2-e2d92005ee12</xr:TypeId>
				<xr:ValueId>56964133-3c3f-4306-8856-ed80f7b9af1e</xr:ValueId>
			</xr:GeneratedType>
			<xr:GeneratedType name="ExternalDataSourceTableRef.BalanceDB.www_balans_dbo_zakaz" category="Ref">
				<xr:TypeId>306a97c3-e56d-4be2-a8b1-fa023daf2e11</xr:TypeId>
				<xr:ValueId>bc435fca-c8a5-4819-8105-b010d0d63305</xr:ValueId>
			</xr:GeneratedType>
			<xr:GeneratedType name="ExternalDataSourceTableList.BalanceDB.www_balans_dbo_zakaz" category="List">
				<xr:TypeId>651072f0-6859-42c4-acee-a5b502c6b4a7</xr:TypeId>
				<xr:ValueId>df63f2ef-eef7-4927-8ae4-2d37ee143bf8</xr:ValueId>
			</xr:GeneratedType>
			<xr:GeneratedType name="ExternalDataSourceTableRecordSet.BalanceDB.www_balans_dbo_zakaz" category="RecordSet">
				<xr:TypeId>26bbb63a-bf6c-4a29-a8e4-3bd3c07310ce</xr:TypeId>
				<xr:ValueId>979f33d1-272c-42da-bb20-d02fe3cfb5ad</xr:ValueId>
			</xr:GeneratedType>
			<xr:GeneratedType name="ExternalDataSourceTableRecordKey.BalanceDB.www_balans_dbo_zakaz" category="RecordKey">
				<xr:TypeId>e92781b7-1a1b-476c-93d2-b33fb117845c</xr:TypeId>
				<xr:ValueId>2715a0d1-a960-4240-94c8-bc9c516dd5f8</xr:ValueId>
			</xr:GeneratedType>
			<xr:GeneratedType name="ExternalDataSourceTableRecordManager.BalanceDB.www_balans_dbo_zakaz" category="RecordManager">
				<xr:TypeId>985992bf-71a4-42e8-972a-459169195162</xr:TypeId>
				<xr:ValueId>6de886a1-ecbb-45bf-814f-0fe6b0f3085e</xr:ValueId>
			</xr:GeneratedType>
		</InternalInfo>
		<Properties>
			<Name>www_balans_dbo_zakaz</Name>
			<Synonym/>
			<Comment/>
			<TableType>Table</TableType>
			<NameInDataSource>www_balans.dbo.zakaz</NameInDataSource>
			<ExpressionInDataSource/>
			<TableDataType>ObjectData</TableDataType>
			<KeyFields>
				<xr:Field>ExternalDataSource.BalanceDB.Table.www_balans_dbo_zakaz.Field.kod</xr:Field>
			</KeyFields>
			<PresentationField/>
			<ParentField/>
			<UnfilledParentValue xsi:nil="true"/>
			<Characteristics/>
			<UseStandardCommands>true</UseStandardCommands>
			<QuickChoice>false</QuickChoice>
			<InputByString>
				<xr:Field>ExternalDataSource.BalanceDB.Table.www_balans_dbo_zakaz.Field.kod</xr:Field>
			</InputByString>
			<CreateOnInput>Auto</CreateOnInput>
			<SearchStringModeOnInputByString>Begin</SearchStringModeOnInputByString>
			<ChoiceDataGetModeOnInputByString>Directly</ChoiceDataGetModeOnInputByString>
			<ChoiceHistoryOnInput>Auto</ChoiceHistoryOnInput>
			<DefaultObjectForm/>
			<DefaultRecordForm/>
			<DefaultListForm/>
			<DefaultChoiceForm/>
			<ObjectPresentation/>
			<ExtendedObjectPresentation/>
			<RecordPresentation/>
			<ExtendedRecordPresentation/>
			<ListPresentation/>
			<ExtendedListPresentation/>
			<Explanation/>
			<IncludeHelpInContents>false</IncludeHelpInContents>
			<ReadOnly>false</ReadOnly>
			<TransactionsIsolationLevel>Auto</TransactionsIsolationLevel>
			<DataVersionField/>
			<EditType>InDialog</EditType>
			<BasedOn/>
			<DataLockFields/>
			<DataLockControlMode>Automatic</DataLockControlMode>
		</Properties>
		<ChildObjects>
			<Field uuid="f5c3b8f9-3b4b-4ded-a4a1-1cf4e3a8efa3">
				<Properties>
					<Name>kod</Name>
					<Synonym/>
					<Comment/>
					<Type>
						<v8:Type>xs:decimal</v8:Type>
						<v8:NumberQualifiers>
							<v8:Digits>10</v8:Digits>
							<v8:FractionDigits>0</v8:FractionDigits>
							<v8:AllowedSign>Any</v8:AllowedSign>
						</v8:NumberQualifiers>
					</Type>
					<PasswordMode>false</PasswordMode>
					<Format/>
					<EditFormat/>
					<ToolTip/>
					<MarkNegatives>false</MarkNegatives>
					<Mask/>
					<MultiLine>false</MultiLine>
					<ExtendedEdit>false</ExtendedEdit>
					<MinValue xsi:nil="true"/>
					<MaxValue xsi:nil="true"/>
					<FillFromFillingValue>false</FillFromFillingValue>
					<FillValue xsi:type="xs:decimal">0</FillValue>
					<FillChecking>DontCheck</FillChecking>
					<ChoiceParameterLinks/>
					<ChoiceParameters/>
					<QuickChoice>Auto</QuickChoice>
					<CreateOnInput>Auto</CreateOnInput>
					<ChoiceHistoryOnInput>Auto</ChoiceHistoryOnInput>
					<ChoiceForm/>
					<NameInDataSource>kod</NameInDataSource>
					<ReadOnly>false</ReadOnly>
					<AllowNull>false</AllowNull>
				</Properties>
			</Field>
			<Field uuid="16867547-8dda-4271-ac84-4f743368ac68">
				<Properties>
					<Name>kod_graf</Name>
					<Synonym/>
					<Comment/>
					<Type>
						<v8:Type>xs:decimal</v8:Type>
						<v8:NumberQualifiers>
							<v8:Digits>10</v8:Digits>
							<v8:FractionDigits>0</v8:FractionDigits>
							<v8:AllowedSign>Any</v8:AllowedSign>
						</v8:NumberQualifiers>
					</Type>
					<PasswordMode>false</PasswordMode>
					<Format/>
					<EditFormat/>
					<ToolTip/>
					<MarkNegatives>false</MarkNegatives>
					<Mask/>
					<MultiLine>false</MultiLine>
					<ExtendedEdit>false</ExtendedEdit>
					<MinValue xsi:nil="true"/>
					<MaxValue xsi:nil="true"/>
					<FillFromFillingValue>false</FillFromFillingValue>
					<FillValue xsi:type="xs:decimal">0</FillValue>
					<FillChecking>DontCheck</FillChecking>
					<ChoiceParameterLinks/>
					<ChoiceParameters/>
					<QuickChoice>Auto</QuickChoice>
					<CreateOnInput>Auto</CreateOnInput>
					<ChoiceHistoryOnInput>Auto</ChoiceHistoryOnInput>
					<ChoiceForm/>
					<NameInDataSource>kod_graf</NameInDataSource>
					<ReadOnly>false</ReadOnly>
					<AllowNull>false</AllowNull>
				</Properties>
			</Field>
			<Field uuid="e938e96a-670a-4cb0-a981-ef691af1305b">
				<Properties>
					<Name>flag</Name>
					<Synonym/>
					<Comment/>
					<Type>
						<v8:Type>xs:string</v8:Type>
						<v8:StringQualifiers>
							<v8:Length>10</v8:Length>
							<v8:AllowedLength>Fixed</v8:AllowedLength>
						</v8:StringQualifiers>
					</Type>
					<PasswordMode>false</PasswordMode>
					<Format/>
					<EditFormat/>
					<ToolTip/>
					<MarkNegatives>false</MarkNegatives>
					<Mask/>
					<MultiLine>false</MultiLine>
					<ExtendedEdit>false</ExtendedEdit>
					<MinValue xsi:nil="true"/>
					<MaxValue xsi:nil="true"/>
					<FillFromFillingValue>false</FillFromFillingValue>
					<FillValue xsi:type="xs:string"/>
					<FillChecking>DontCheck</FillChecking>
					<ChoiceParameterLinks/>
					<ChoiceParameters/>
					<QuickChoice>Auto</QuickChoice>
					<CreateOnInput>Auto</CreateOnInput>
					<ChoiceHistoryOnInput>Auto</ChoiceHistoryOnInput>
					<ChoiceForm/>
					<NameInDataSource>flag</NameInDataSource>
					<ReadOnly>false</ReadOnly>
					<AllowNull>false</AllowNull>
				</Properties>
			</Field>
			<Field uuid="21b5c562-d600-4433-88b8-90e005034207">
				<Properties>
					<Name>txt_1</Name>
					<Synonym/>
					<Comment/>
					<Type>
						<v8:Type>xs:string</v8:Type>
						<v8:StringQualifiers>
							<v8:Length>50</v8:Length>
							<v8:AllowedLength>Fixed</v8:AllowedLength>
						</v8:StringQualifiers>
					</Type>
					<PasswordMode>false</PasswordMode>
					<Format/>
					<EditFormat/>
					<ToolTip/>
					<MarkNegatives>false</MarkNegatives>
					<Mask/>
					<MultiLine>false</MultiLine>
					<ExtendedEdit>false</ExtendedEdit>
					<MinValue xsi:nil="true"/>
					<MaxValue xsi:nil="true"/>
					<FillFromFillingValue>false</FillFromFillingValue>
					<FillValue xsi:type="xs:string"/>
					<FillChecking>DontCheck</FillChecking>
					<ChoiceParameterLinks/>
					<ChoiceParameters/>
					<QuickChoice>Auto</QuickChoice>
					<CreateOnInput>Auto</CreateOnInput>
					<ChoiceHistoryOnInput>Auto</ChoiceHistoryOnInput>
					<ChoiceForm/>
					<NameInDataSource>txt_1</NameInDataSource>
					<ReadOnly>false</ReadOnly>
					<AllowNull>false</AllowNull>
				</Properties>
			</Field>
			<Field uuid="145b09a6-fac5-4597-bff1-636f010a2af6">
				<Properties>
					<Name>txt_2</Name>
					<Synonym/>
					<Comment/>
					<Type>
						<v8:Type>xs:string</v8:Type>
						<v8:StringQualifiers>
							<v8:Length>50</v8:Length>
							<v8:AllowedLength>Fixed</v8:AllowedLength>
						</v8:StringQualifiers>
					</Type>
					<PasswordMode>false</PasswordMode>
					<Format/>
					<EditFormat/>
					<ToolTip/>
					<MarkNegatives>false</MarkNegatives>
					<Mask/>
					<MultiLine>false</MultiLine>
					<ExtendedEdit>false</ExtendedEdit>
					<MinValue xsi:nil="true"/>
					<MaxValue xsi:nil="true"/>
					<FillFromFillingValue>false</FillFromFillingValue>
					<FillValue xsi:type="xs:string"/>
					<FillChecking>DontCheck</FillChecking>
					<ChoiceParameterLinks/>
					<ChoiceParameters/>
					<QuickChoice>Auto</QuickChoice>
					<CreateOnInput>Auto</CreateOnInput>
					<ChoiceHistoryOnInput>Auto</ChoiceHistoryOnInput>
					<ChoiceForm/>
					<NameInDataSource>txt_2</NameInDataSource>
					<ReadOnly>false</ReadOnly>
					<AllowNull>false</AllowNull>
				</Properties>
			</Field>
			<Field uuid="307923b5-7d2f-4f44-9a24-a1c427280d2d">
				<Properties>
					<Name>txt_3</Name>
					<Synonym/>
					<Comment/>
					<Type>
						<v8:Type>xs:string</v8:Type>
						<v8:StringQualifiers>
							<v8:Length>50</v8:Length>
							<v8:AllowedLength>Fixed</v8:AllowedLength>
						</v8:StringQualifiers>
					</Type>
					<PasswordMode>false</PasswordMode>
					<Format/>
					<EditFormat/>
					<ToolTip/>
					<MarkNegatives>false</MarkNegatives>
					<Mask/>
					<MultiLine>false</MultiLine>
					<ExtendedEdit>false</ExtendedEdit>
					<MinValue xsi:nil="true"/>
					<MaxValue xsi:nil="true"/>
					<FillFromFillingValue>false</FillFromFillingValue>
					<FillValue xsi:type="xs:string"/>
					<FillChecking>DontCheck</FillChecking>
					<ChoiceParameterLinks/>
					<ChoiceParameters/>
					<QuickChoice>Auto</QuickChoice>
					<CreateOnInput>Auto</CreateOnInput>
					<ChoiceHistoryOnInput>Auto</ChoiceHistoryOnInput>
					<ChoiceForm/>
					<NameInDataSource>txt_3</NameInDataSource>
					<ReadOnly>false</ReadOnly>
					<AllowNull>false</AllowNull>
				</Properties>
			</Field>
		</ChildObjects>
	</Table>
</MetaDataObject>